neuroshard/__init__.py
neuroshard/cli.py
neuroshard/grpc_server.py
neuroshard/runner.py
neuroshard/version.py
neuroshard/core/__init__.py
neuroshard/core/crypto/__init__.py
neuroshard/core/crypto/ecdsa.py
neuroshard/core/economics/__init__.py
neuroshard/core/economics/constants.py
neuroshard/core/economics/ledger.py
neuroshard/core/economics/market.py
neuroshard/core/economics/wallet.py
neuroshard/core/model/__init__.py
neuroshard/core/model/dynamic.py
neuroshard/core/model/llm.py
neuroshard/core/model/registry.py
neuroshard/core/model/scaler.py
neuroshard/core/model/tokenizer.py
neuroshard/core/network/__init__.py
neuroshard/core/network/connection_pool.py
neuroshard/core/network/dht.py
neuroshard/core/network/dht_plan.py
neuroshard/core/network/dht_proof_store.py
neuroshard/core/network/dht_protocol.py
neuroshard/core/network/dht_service.py
neuroshard/core/network/encrypted_channel.py
neuroshard/core/network/grpc.py
neuroshard/core/network/nat.py
neuroshard/core/network/nat_traversal.py
neuroshard/core/network/p2p.py
neuroshard/core/network/p2p_data.py
neuroshard/core/swarm/__init__.py
neuroshard/core/swarm/aggregation.py
neuroshard/core/swarm/buffers.py
neuroshard/core/swarm/checkpoint.py
neuroshard/core/swarm/compute.py
neuroshard/core/swarm/diloco.py
neuroshard/core/swarm/factory.py
neuroshard/core/swarm/heartbeat.py
neuroshard/core/swarm/logger.py
neuroshard/core/swarm/router.py
neuroshard/core/swarm/service.py
neuroshard/core/swarm/trainer.py
neuroshard/core/training/__init__.py
neuroshard/core/training/allreduce.py
neuroshard/core/training/checkpoint.py
neuroshard/core/training/distributed.py
neuroshard/core/training/production.py
neuroshard/tracker/__init__.py
neuroshard/tracker/server.py
neuroshard/ui/__init__.py
neuroshard/ui/app.py
neuroshard/ui/templates/index.html
neuroshard/utils/__init__.py
neuroshard/utils/autostart.py
neuroshard/utils/hardware.py
neuroshard/utils/serialization.py
protos/__init__.py
protos/neuroshard.proto
protos/neuroshard_pb2.py
nextaitech-0.0.4.dist-info/METADATA
nextaitech-0.0.4.dist-info/WHEEL
nextaitech-0.0.4.dist-info/entry_points.txt
nextaitech-0.0.4.dist-info/top_level.txt
nextaitech-0.0.4.dist-info/RECORD
